djelia_sdk/__init__.py
djelia_sdk/_base_client.py
djelia_sdk/_client.py
djelia_sdk/_compat.py
djelia_sdk/_constants.py
djelia_sdk/_exceptions.py
djelia_sdk/_files.py
djelia_sdk/_models.py
djelia_sdk/_qs.py
djelia_sdk/_resource.py
djelia_sdk/_response.py
djelia_sdk/_streaming.py
djelia_sdk/_types.py
djelia_sdk/_version.py
djelia_sdk/py.typed
djelia_sdk/_utils/__init__.py
djelia_sdk/_utils/_compat.py
djelia_sdk/_utils/_datetime_parse.py
djelia_sdk/_utils/_logs.py
djelia_sdk/_utils/_proxy.py
djelia_sdk/_utils/_reflection.py
djelia_sdk/_utils/_resources_proxy.py
djelia_sdk/_utils/_streams.py
djelia_sdk/_utils/_sync.py
djelia_sdk/_utils/_transform.py
djelia_sdk/_utils/_typing.py
djelia_sdk/_utils/_utils.py
djelia_sdk/lib/.keep
djelia_sdk/resources/__init__.py
djelia_sdk/resources/api/__init__.py
djelia_sdk/resources/api/api.py
djelia_sdk/resources/api/v1/__init__.py
djelia_sdk/resources/api/v1/v1.py
djelia_sdk/resources/api/v1/models/__init__.py
djelia_sdk/resources/api/v1/models/models.py
djelia_sdk/resources/api/v1/models/transcribe.py
djelia_sdk/resources/api/v1/models/translate.py
djelia_sdk/types/__init__.py
djelia_sdk/types/api/__init__.py
djelia_sdk/types/api/v1/__init__.py
djelia_sdk/types/api/v1/model_create_speech_params.py
djelia_sdk/types/api/v1/models/__init__.py
djelia_sdk/types/api/v1/models/french_transcription_response.py
djelia_sdk/types/api/v1/models/transcribe_create_transcription_params.py
djelia_sdk/types/api/v1/models/transcribe_create_transcription_response.py
djelia_sdk/types/api/v1/models/transcribe_stream_transcription_params.py
djelia_sdk/types/api/v1/models/transcribe_stream_transcription_response.py
djelia_sdk/types/api/v1/models/transcription_segment.py
djelia_sdk/types/api/v1/models/translate_create_translation_params.py
djelia_sdk/types/api/v1/models/translate_create_translation_response.py
djelia_sdk/types/api/v1/models/translate_list_supported_languages_response.py
djelia_sdk/types/api/v1/models/translation_language.py
djelia_sdk-2.0.3.dist-info/METADATA
djelia_sdk-2.0.3.dist-info/WHEEL
djelia_sdk-2.0.3.dist-info/licenses/LICENSE
djelia_sdk-2.0.3.dist-info/RECORD
